jupyter_database_connector/jupyter_database_connector.py
jupyter_database_connector-0.1.0.dist-info/METADATA
jupyter_database_connector-0.1.0.dist-info/WHEEL
jupyter_database_connector-0.1.0.dist-info/top_level.txt
jupyter_database_connector-0.1.0.dist-info/RECORD
