Metadata-Version: 2.1
Name: jupyter-database-connector
Version: 0.1.0
Requires-Dist: sqlalchemy
Requires-Dist: jupyter-server
